awesome_monaco/__init__.py
awesome_monaco/start.py
awesome_monaco/brains/__init__.py
awesome_monaco/brains/build_data.py
awesome_monaco/brains/config.py
awesome_monaco/brains/experiments.py
awesome_monaco/brains/parser.py
awesome_monaco/brains/report.py
awesome_monaco/brains/utils.py
awesome_monaco-0.0.2.dist-info/METADATA
awesome_monaco-0.0.2.dist-info/WHEEL
awesome_monaco-0.0.2.dist-info/licenses/License.mit
awesome_monaco-0.0.2.dist-info/RECORD
