Metadata-Version: 2.1
Name: awesome_monaco
Version: 0.0.2
Summary: Monac Studing Project
Project-URL: Homepage, https://github.com/FedXL/Monaco-Monaco
Project-URL: Bug Tracker, https://github.com/FedXL/Monaco-Monaco/issues
Author-email: Fedor Kuruts <fedorkuruts@gmail.com>
License-File: License.mit
Classifier: License :: OSI Approved :: MIT License
Classifier: Operating System :: OS Independent
Classifier: Programming Language :: Python :: 3
Requires-Python: >=3.10
